{
    "ASHP": {
        "kind": {
            "category": "DROPSHIP",
            "starship": true
        },
        "display": {
            "width": 3,
            "height": 3,
            "tiles": "structure-alien-dropship",
            "offset": 0
        },
        "production": {
            "category": "NONE",
            "cash": 0,
            "energy": 0,
            "research": 0
        },
        "usage": {
            "cash": 0,
            "energy": 0
        },
        "storage": {
            "category": "TROOP FACTORY HOVER",
            "size": 8
        },
        "build": {
            "cost": 800,
            "placement": "ANYWHERE"
        },
        "encyclopedia": {
            "image": "encyclopedia-ashp",
            "next": "AAIR",
            "prev": null
        }
    },
    "AAIR": {
        "kind": {
            "category": "AIRPORT",
            "starship": false
        },
        "display": {
            "width": 3,
            "height": 4,
            "tiles": "structure-alien",
            "offset": 0
        },
        "production": {
            "category": "HOVER",
            "cash": 0,
            "energy": 0,
            "research": 0
        },
        "usage": {
            "cash": 0,
            "energy": 50
        },
        "storage": {
            "category": "HOVER",
            "size": 12
        },
        "build": {
            "cost": 225,
            "placement": "B-ROAD"
        },
        "encyclopedia": {
            "image": "encyclopedia-aair",
            "next": null,
            "prev": "ASHP"
        }
    }
}